pyaesthetics/__init__.py
pyaesthetics/analysis.py
pyaesthetics/brightness.py
pyaesthetics/colordetection.py
pyaesthetics/colorfulness.py
pyaesthetics/contrast.py
pyaesthetics/data/face1.png
pyaesthetics/facedetection.py
pyaesthetics/linesdetection.py
pyaesthetics/quadtreedecomposition.py
pyaesthetics/saturation.py
pyaesthetics/selfsimilarity.py
pyaesthetics/spacebaseddecomposition.py
pyaesthetics/symmetry.py
pyaesthetics/utils.py
pyaesthetics/visualcomplexity.py
pyaesthetics-0.0.8.9.dist-info/LICENSE
pyaesthetics-0.0.8.9.dist-info/METADATA
pyaesthetics-0.0.8.9.dist-info/WHEEL
pyaesthetics-0.0.8.9.dist-info/RECORD
