Metadata-Version: 2.1
Name: pyaesthetics
Version: 0.0.8.9
Summary: A python package to estimate visual features about the aesthetic appearance of still images.
License: GPL-3.0
Keywords: Image,Analysis,Aesthetic,Visual,Features,Empirical Aesthetic
Author: Giulio Gabrieli
Author-email: gack94@gmail.com
Requires-Python: >=3.10,<4.0
Classifier: Development Status :: 5 - Production/Stable
Classifier: Intended Audience :: Science/Research
Classifier: License :: OSI Approved :: GNU General Public License v3 (GPLv3)
Classifier: Operating System :: MacOS
Classifier: Operating System :: Microsoft :: Windows
Classifier: Operating System :: POSIX
Classifier: Operating System :: Unix
Classifier: Programming Language :: Python
Classifier: Programming Language :: Python :: 3
Classifier: Programming Language :: Python :: 3.10
Classifier: Programming Language :: Python :: 3.11
Classifier: Programming Language :: Python :: 3.12
Classifier: Topic :: Multimedia :: Graphics
Classifier: Topic :: Scientific/Engineering
Classifier: Topic :: Scientific/Engineering :: Image Processing
Classifier: Topic :: Scientific/Engineering :: Information Analysis
Classifier: Topic :: Scientific/Engineering :: Visualization
Classifier: Typing :: Typed
Requires-Dist: imutils (>=0.5,<0.6)
Requires-Dist: matplotlib (>=3.9,<4.0)
Requires-Dist: numpy (>=2.0,<3.0)
Requires-Dist: opencv-python (>=4.10,<5.0)
Requires-Dist: pandas (>=2.2,<3.0)
Requires-Dist: pillow (>=10.4,<11.0)
Requires-Dist: pytesseract (>=0.3,<0.4)
Requires-Dist: rembg (>=2.0.59,<3.0.0)
Requires-Dist: scikit-image (>=0.24,<0.25)
Requires-Dist: scipy (>=1.14,<2.0)
Requires-Dist: tqdm (>=4.66,<5.0)
